qttools/__init__.py
qttools/checkablecombo.py
qttools/chekablemapmodel.py
qttools/const.py
qttools/mapmodel.py
qttools/plotwidget.py
qttools-0.0.1.dist-info/METADATA
qttools-0.0.1.dist-info/WHEEL
qttools-0.0.1.dist-info/top_level.txt
qttools-0.0.1.dist-info/RECORD
