Metadata-Version: 2.1
Name: qttools
Version: 0.0.1
Summary: Assorted PyQt5 tools
Home-page: UNKNOWN
Author: igrekus
Author-email: UNKNOWN
License: UNKNOWN
Keywords: python,pyqt5
Platform: UNKNOWN
Classifier: Development Status :: 3 - Alpha
Classifier: Intended Audience :: Education
Classifier: Programming Language :: Python :: 3
Classifier: Operating System :: Microsoft :: Windows
